mcp_beeper_texts/__init__.py
mcp_beeper_texts/__main__.py
mcp_beeper_texts/db.py
mcp_beeper_texts/models.py
mcp_beeper_texts/queries.py
mcp_beeper_texts/server.py
mcp_beeper_texts-0.0.2.dist-info/METADATA
mcp_beeper_texts-0.0.2.dist-info/WHEEL
mcp_beeper_texts-0.0.2.dist-info/entry_points.txt
mcp_beeper_texts-0.0.2.dist-info/licenses/LICENSE
mcp_beeper_texts-0.0.2.dist-info/RECORD
