Metadata-Version: 2.4
Name: mcp-beeper-texts
Version: 0.0.2
Summary: A local MCP server for Beeper Texts on macOS.
Project-URL: Homepage, https://github.com/tetmin/mcp-beeper-texts
Project-URL: Issues, https://github.com/tetmin/mcp-beeper-texts/issues
Author: Tom Etminan
License-Expression: MIT
License-File: LICENSE
Classifier: Development Status :: 3 - Alpha
Classifier: Intended Audience :: Developers
Classifier: License :: OSI Approved :: MIT License
Classifier: Operating System :: MacOS
Classifier: Programming Language :: Python :: 3
Classifier: Programming Language :: Python :: 3.10
Classifier: Programming Language :: Python :: 3.11
Classifier: Programming Language :: Python :: 3.12
Requires-Python: >=3.10
Requires-Dist: mcp[cli]>=1.12.3
Requires-Dist: pillow>=10.0.0
Requires-Dist: pydantic
